pyzac/__init__.py
pyzac/pyzac_base.py
pyzac/zeromq_demo_pub.py
pyzac/zeromq_demo_sub.py
pyzac-0.0.6.dist-info/LICENSE
pyzac-0.0.6.dist-info/METADATA
pyzac-0.0.6.dist-info/WHEEL
pyzac-0.0.6.dist-info/top_level.txt
pyzac-0.0.6.dist-info/RECORD
